pygments-gdscript/__init__.py
pygments-gdscript/gdscript.py
pygments_gdscript/__init__.py
pygments_gdscript/gdscript.py
pygments_gdscript-1.0.4.dist-info/METADATA
pygments_gdscript-1.0.4.dist-info/WHEEL
pygments_gdscript-1.0.4.dist-info/entry_points.txt
pygments_gdscript-1.0.4.dist-info/top_level.txt
pygments_gdscript-1.0.4.dist-info/RECORD
