Metadata-Version: 2.4
Name: pygments_gdscript
Version: 1.0.4
Summary: A small example package
Home-page: https://github.com/ZackeryRSmith/pygments-gdscript
Author: ZackeryRSmith
Author-email: zackery.smith82307@gmail.com
Classifier: Programming Language :: Python :: 3
Classifier: License :: OSI Approved :: MIT License
Classifier: Operating System :: OS Independent
Dynamic: author
Dynamic: author-email
Dynamic: classifier
Dynamic: description
Dynamic: description-content-type
Dynamic: home-page
Dynamic: summary
